Metadata-Version: 2.1
Name: oebuild
Version: 0.2.0.0
Summary: UNKNOWN
Home-page: UNKNOWN
Author: alichinese
Author-email: 
License: UNKNOWN
Platform: UNKNOWN
Classifier: Programming Language :: Python :: 3
Classifier: License :: OSI Approved :: Apache Software License
Classifier: Operating System :: POSIX :: Linux
Requires-Python: >=3.8
License-File: LICENSE.txt
Requires-Dist: GitPython
Requires-Dist: PyYaml
Requires-Dist: dataclasses
Requires-Dist: docker
Requires-Dist: kconfiglib
Requires-Dist: packaging
Requires-Dist: prettytable
Requires-Dist: reprint
Requires-Dist: ruamel.yaml
Requires-Dist: setuptools
